lineaSSP/__init__.py
lineaSSP/api/__init__.py
lineaSSP/api/asteroid.py
lineaSSP/api/base.py
lineaSSP/api/occviz.py
lineaSSP/api/prediction.py
lineaSSP-0.1.2.dist-info/LICENSE
lineaSSP-0.1.2.dist-info/METADATA
lineaSSP-0.1.2.dist-info/WHEEL
lineaSSP-0.1.2.dist-info/top_level.txt
lineaSSP-0.1.2.dist-info/RECORD
