Metadata-Version: 2.1
Name: lineaSSP
Version: 0.1.2
Summary: A Python module to use or retrieve information from the LIneA Solar System Portal.
Author-email: LIneA Team <helpdesk@linea.org.br>
License: MIT
Project-URL: Homepage, https://github.com/linea-it/lineaSSP
Requires-Python: >=3.8
License-File: LICENSE
Requires-Dist: numpy
Requires-Dist: scipy
Requires-Dist: sora-astro
Requires-Dist: astropy
Requires-Dist: cartopy
Requires-Dist: tqdm
Provides-Extra: dev
Requires-Dist: pytest>=4.4.1; extra == "dev"
Requires-Dist: twine<5.0,>=4.0; extra == "dev"
